agentlin_client/__init__.py
agentlin_client/_base_client.py
agentlin_client/_client.py
agentlin_client/_compat.py
agentlin_client/_constants.py
agentlin_client/_exceptions.py
agentlin_client/_files.py
agentlin_client/_models.py
agentlin_client/_qs.py
agentlin_client/_resource.py
agentlin_client/_response.py
agentlin_client/_streaming.py
agentlin_client/_types.py
agentlin_client/_version.py
agentlin_client/pagination.py
agentlin_client/py.typed
agentlin_client/_utils/__init__.py
agentlin_client/_utils/_compat.py
agentlin_client/_utils/_datetime_parse.py
agentlin_client/_utils/_json.py
agentlin_client/_utils/_logs.py
agentlin_client/_utils/_proxy.py
agentlin_client/_utils/_reflection.py
agentlin_client/_utils/_resources_proxy.py
agentlin_client/_utils/_streams.py
agentlin_client/_utils/_sync.py
agentlin_client/_utils/_transform.py
agentlin_client/_utils/_typing.py
agentlin_client/_utils/_utils.py
agentlin_client/lib/.keep
agentlin_client/resources/__init__.py
agentlin_client/resources/env.py
agentlin_client/resources/tasks.py
agentlin_client/types/__init__.py
agentlin_client/types/annotation_container_file_citation.py
agentlin_client/types/annotation_container_file_citation_param.py
agentlin_client/types/annotation_file_citation.py
agentlin_client/types/annotation_file_citation_param.py
agentlin_client/types/annotation_file_path.py
agentlin_client/types/annotation_file_path_param.py
agentlin_client/types/annotation_url_citation.py
agentlin_client/types/annotation_url_citation_param.py
agentlin_client/types/audio_content_item.py
agentlin_client/types/audio_content_item_param.py
agentlin_client/types/env_clean_session_params.py
agentlin_client/types/env_close_params.py
agentlin_client/types/env_close_response.py
agentlin_client/types/env_create_params.py
agentlin_client/types/env_create_response.py
agentlin_client/types/env_info.py
agentlin_client/types/env_info_response.py
agentlin_client/types/env_list_params.py
agentlin_client/types/env_observation_params.py
agentlin_client-1.14.0.dist-info/METADATA
agentlin_client-1.14.0.dist-info/WHEEL
agentlin_client-1.14.0.dist-info/licenses/LICENSE
agentlin_client-1.14.0.dist-info/RECORD
